nrkdownload/__init__.py
nrkdownload/__main__.py
nrkdownload/cli.py
nrkdownload/download.py
nrkdownload/nrk_tv.py
nrkdownload/py.typed
nrkdownload-3.2.6.dist-info/METADATA
nrkdownload-3.2.6.dist-info/WHEEL
nrkdownload-3.2.6.dist-info/entry_points.txt
nrkdownload-3.2.6.dist-info/top_level.txt
nrkdownload-3.2.6.dist-info/RECORD
