Metadata-Version: 2.2
Name: nrkdownload
Version: 3.2.6
Summary: Download content from NRK TV.
Author-email: Martin Høy <martin@hoy.priv.no>
Classifier: Development Status :: 5 - Production/Stable
Classifier: Typing :: Typed
Classifier: Environment :: Console
Classifier: Programming Language :: Python :: 3
Classifier: Programming Language :: Python :: 3.10
Classifier: Programming Language :: Python :: 3.11
Classifier: Programming Language :: Python :: 3.12
Classifier: Programming Language :: Python :: 3.13
Requires-Python: >=3.10
Requires-Dist: loguru>=0.7.3
Requires-Dist: pydantic>=2.10.6
Requires-Dist: typer>=0.15.1
Requires-Dist: requests>=2.32.3
Requires-Dist: python-ffmpeg>=2.0.12
